alife/__init__.py
alife/cli.py
alife/diary.py
alife/py.typed
alife-0.1.0.dist-info/entry_points.txt
alife-0.1.0.dist-info/WHEEL
alife-0.1.0.dist-info/METADATA
alife-0.1.0.dist-info/RECORD
