Metadata-Version: 2.1
Name: alife
Version: 0.1.0
Summary: Git a Life
License: MIT
Author: Bijay Gurung
Author-email: bijay.learning@gmail.com
Requires-Python: >=3.7,<4.0
Classifier: License :: OSI Approved :: MIT License
Classifier: Programming Language :: Python :: 3
Classifier: Programming Language :: Python :: 3.7
Classifier: Programming Language :: Python :: 3.8
Classifier: Programming Language :: Python :: 3.9
Requires-Dist: GitPython (>=3.1.18,<4.0.0)
Requires-Dist: typer (>=0.3.2,<0.4.0)
